{
  "schema": "rapp-static-industry-write-receipt/1.0",
  "generated": "2026-07-10T20:30:00Z",
  "adapter_id": "eia_923",
  "capability_code": "optimize",
  "route_count": 1,
  "write_intent_count": 0,
  "receipt": {
    "receipt_id": "receipt_0f2447e9efe5807f96b6",
    "operation": "simulate_optimize",
    "resource_id": "compliance_findings",
    "accepted": true,
    "simulated": true,
    "status": "accepted",
    "processed_at": "2026-07-10T20:30:00Z",
    "idempotency_key": "idem_0e93f7988fe925310bf3"
  }
}
