{
  "schema": "rapp-static-industry-collection/1.0",
  "generated": "2026-07-10T20:30:00Z",
  "adapter_id": "bloomberg_market_data",
  "resource_id": "portfolios",
  "count": 3,
  "value": [
    {
      "record_id": "ref_feddbbe3add8de927ef2",
      "portfolio_id": "ref_feddbbe3add8de927ef2",
      "strategy_code": "strategy_1",
      "drift_percent": 100.0,
      "status": "active"
    },
    {
      "record_id": "ref_83eae18566d1ab619a6f",
      "portfolio_id": "ref_83eae18566d1ab619a6f",
      "strategy_code": "strategy_2",
      "drift_percent": 125.0,
      "status": "pending"
    },
    {
      "record_id": "ref_990f69d4b5717f8a2cbc",
      "portfolio_id": "ref_990f69d4b5717f8a2cbc",
      "strategy_code": "strategy_3",
      "drift_percent": 150.0,
      "status": "complete"
    }
  ]
}
