{
  "schema": "rapp-static-industry-collection/1.0",
  "generated": "2026-07-10T20:30:00Z",
  "adapter_id": "tms",
  "resource_id": "inventory_items",
  "count": 3,
  "value": [
    {
      "record_id": "ref_fed5bbf1f630f44cf939",
      "item_id": "ref_fed5bbf1f630f44cf939",
      "location_code": "location_1",
      "quantity_available": 10,
      "status": "active"
    },
    {
      "record_id": "ref_11152e653defd75fe09f",
      "item_id": "ref_11152e653defd75fe09f",
      "location_code": "location_2",
      "quantity_available": 11,
      "status": "pending"
    },
    {
      "record_id": "ref_4d8a7ff6a4049449a3e3",
      "item_id": "ref_4d8a7ff6a4049449a3e3",
      "location_code": "location_3",
      "quantity_available": 12,
      "status": "complete"
    }
  ]
}
