{
  "swagger": "2.0",
  "info": {
    "title": "RAPP Static ServiceNow",
    "description": "Unauthenticated no-PII static GET adapter. Write operations are receipt previews and never mutate an external product.",
    "version": "1.0.0"
  },
  "host": "raw.githubusercontent.com",
  "basePath": "/kody-w/rapp-static-apis/main/industry-templates",
  "schemes": [
    "https"
  ],
  "consumes": [],
  "produces": [
    "application/json"
  ],
  "paths": {
    "/api/v1/service_now/audit_events.json": {
      "get": {
        "operationId": "GetServiceNowAuditEventsCollection",
        "summary": "List static audit_events",
        "produces": [
          "application/json"
        ],
        "responses": {
          "200": {
            "description": "Deterministic no-PII collection",
            "schema": {
              "type": "object",
              "additionalProperties": false,
              "required": [
                "schema",
                "generated",
                "adapter_id",
                "resource_id",
                "count",
                "value"
              ],
              "properties": {
                "schema": {
                  "type": "string",
                  "enum": [
                    "rapp-static-industry-collection/1.0"
                  ]
                },
                "generated": {
                  "type": "string",
                  "format": "date-time"
                },
                "adapter_id": {
                  "type": "string",
                  "enum": [
                    "service_now"
                  ]
                },
                "resource_id": {
                  "type": "string",
                  "enum": [
                    "audit_events"
                  ]
                },
                "count": {
                  "type": "integer",
                  "format": "int32"
                },
                "value": {
                  "type": "array",
                  "items": {
                    "type": "object",
                    "additionalProperties": false,
                    "required": [
                      "record_id",
                      "event_id",
                      "event_type",
                      "result_code",
                      "occurred_at"
                    ],
                    "properties": {
                      "record_id": {
                        "type": "string",
                        "description": "Stable deterministic record identifier."
                      },
                      "event_id": {
                        "type": "string"
                      },
                      "event_type": {
                        "type": "string"
                      },
                      "result_code": {
                        "type": "string"
                      },
                      "occurred_at": {
                        "type": "string",
                        "format": "date-time"
                      }
                    }
                  }
                }
              }
            }
          }
        },
        "x-ms-visibility": "important"
      }
    },
    "/api/v1/service_now/audit_events/records/{record_id}.json": {
      "get": {
        "operationId": "GetServiceNowAuditEventsRecord",
        "summary": "Get one static audit_events record",
        "produces": [
          "application/json"
        ],
        "parameters": [
          {
            "name": "record_id",
            "in": "path",
            "required": true,
            "type": "string"
          }
        ],
        "responses": {
          "200": {
            "description": "Deterministic no-PII record",
            "schema": {
              "type": "object",
              "additionalProperties": false,
              "required": [
                "schema",
                "generated",
                "adapter_id",
                "resource_id",
                "record"
              ],
              "properties": {
                "schema": {
                  "type": "string",
                  "enum": [
                    "rapp-static-industry-record/1.0"
                  ]
                },
                "generated": {
                  "type": "string",
                  "format": "date-time"
                },
                "adapter_id": {
                  "type": "string",
                  "enum": [
                    "service_now"
                  ]
                },
                "resource_id": {
                  "type": "string",
                  "enum": [
                    "audit_events"
                  ]
                },
                "record": {
                  "type": "object",
                  "additionalProperties": false,
                  "required": [
                    "record_id",
                    "event_id",
                    "event_type",
                    "result_code",
                    "occurred_at"
                  ],
                  "properties": {
                    "record_id": {
                      "type": "string",
                      "description": "Stable deterministic record identifier."
                    },
                    "event_id": {
                      "type": "string"
                    },
                    "event_type": {
                      "type": "string"
                    },
                    "result_code": {
                      "type": "string"
                    },
                    "occurred_at": {
                      "type": "string",
                      "format": "date-time"
                    }
                  }
                }
              }
            }
          },
          "404": {
            "description": "Unknown deterministic record ID"
          }
        },
        "x-ms-visibility": "important"
      }
    },
    "/api/v1/service_now/changes.json": {
      "get": {
        "operationId": "GetServiceNowChangesCollection",
        "summary": "List static changes",
        "produces": [
          "application/json"
        ],
        "responses": {
          "200": {
            "description": "Deterministic no-PII collection",
            "schema": {
              "type": "object",
              "additionalProperties": false,
              "required": [
                "schema",
                "generated",
                "adapter_id",
                "resource_id",
                "count",
                "value"
              ],
              "properties": {
                "schema": {
                  "type": "string",
                  "enum": [
                    "rapp-static-industry-collection/1.0"
                  ]
                },
                "generated": {
                  "type": "string",
                  "format": "date-time"
                },
                "adapter_id": {
                  "type": "string",
                  "enum": [
                    "service_now"
                  ]
                },
                "resource_id": {
                  "type": "string",
                  "enum": [
                    "changes"
                  ]
                },
                "count": {
                  "type": "integer",
                  "format": "int32"
                },
                "value": {
                  "type": "array",
                  "items": {
                    "type": "object",
                    "additionalProperties": false,
                    "required": [
                      "record_id",
                      "change_id",
                      "change_type",
                      "risk_code",
                      "status"
                    ],
                    "properties": {
                      "record_id": {
                        "type": "string",
                        "description": "Stable deterministic record identifier."
                      },
                      "change_id": {
                        "type": "string"
                      },
                      "change_type": {
                        "type": "string"
                      },
                      "risk_code": {
                        "type": "string"
                      },
                      "status": {
                        "type": "string"
                      }
                    }
                  }
                }
              }
            }
          }
        },
        "x-ms-visibility": "important"
      }
    },
    "/api/v1/service_now/changes/records/{record_id}.json": {
      "get": {
        "operationId": "GetServiceNowChangesRecord",
        "summary": "Get one static changes record",
        "produces": [
          "application/json"
        ],
        "parameters": [
          {
            "name": "record_id",
            "in": "path",
            "required": true,
            "type": "string"
          }
        ],
        "responses": {
          "200": {
            "description": "Deterministic no-PII record",
            "schema": {
              "type": "object",
              "additionalProperties": false,
              "required": [
                "schema",
                "generated",
                "adapter_id",
                "resource_id",
                "record"
              ],
              "properties": {
                "schema": {
                  "type": "string",
                  "enum": [
                    "rapp-static-industry-record/1.0"
                  ]
                },
                "generated": {
                  "type": "string",
                  "format": "date-time"
                },
                "adapter_id": {
                  "type": "string",
                  "enum": [
                    "service_now"
                  ]
                },
                "resource_id": {
                  "type": "string",
                  "enum": [
                    "changes"
                  ]
                },
                "record": {
                  "type": "object",
                  "additionalProperties": false,
                  "required": [
                    "record_id",
                    "change_id",
                    "change_type",
                    "risk_code",
                    "status"
                  ],
                  "properties": {
                    "record_id": {
                      "type": "string",
                      "description": "Stable deterministic record identifier."
                    },
                    "change_id": {
                      "type": "string"
                    },
                    "change_type": {
                      "type": "string"
                    },
                    "risk_code": {
                      "type": "string"
                    },
                    "status": {
                      "type": "string"
                    }
                  }
                }
              }
            }
          },
          "404": {
            "description": "Unknown deterministic record ID"
          }
        },
        "x-ms-visibility": "important"
      }
    },
    "/api/v1/service_now/receipts/analyze.json": {
      "get": {
        "operationId": "SimulateServiceNowAnalyze",
        "summary": "Get a deterministic write-simulation receipt; no mutation",
        "produces": [
          "application/json"
        ],
        "responses": {
          "200": {
            "description": "Static simulated-write receipt",
            "schema": {
              "type": "object",
              "additionalProperties": false,
              "required": [
                "schema",
                "generated",
                "adapter_id",
                "capability_code",
                "route_count",
                "write_intent_count",
                "receipt"
              ],
              "properties": {
                "schema": {
                  "type": "string",
                  "enum": [
                    "rapp-static-industry-write-receipt/1.0"
                  ]
                },
                "generated": {
                  "type": "string",
                  "format": "date-time"
                },
                "adapter_id": {
                  "type": "string",
                  "enum": [
                    "service_now"
                  ]
                },
                "capability_code": {
                  "type": "string",
                  "enum": [
                    "analyze"
                  ]
                },
                "route_count": {
                  "type": "integer",
                  "format": "int32"
                },
                "write_intent_count": {
                  "type": "integer",
                  "format": "int32"
                },
                "receipt": {
                  "type": "object",
                  "additionalProperties": false,
                  "required": [
                    "receipt_id",
                    "operation",
                    "resource_id",
                    "accepted",
                    "simulated",
                    "status",
                    "processed_at",
                    "idempotency_key"
                  ],
                  "properties": {
                    "receipt_id": {
                      "type": "string"
                    },
                    "operation": {
                      "type": "string"
                    },
                    "resource_id": {
                      "type": "string"
                    },
                    "accepted": {
                      "type": "boolean"
                    },
                    "simulated": {
                      "type": "boolean",
                      "enum": [
                        true
                      ]
                    },
                    "status": {
                      "type": "string",
                      "enum": [
                        "accepted",
                        "rejected",
                        "validation_failed"
                      ]
                    },
                    "processed_at": {
                      "type": "string",
                      "format": "date-time"
                    },
                    "idempotency_key": {
                      "type": "string"
                    }
                  }
                }
              }
            }
          }
        },
        "x-ms-visibility": "advanced"
      }
    },
    "/api/v1/service_now/receipts/analyzepriority.json": {
      "get": {
        "operationId": "SimulateServiceNowAnalyzepriority",
        "summary": "Get a deterministic write-simulation receipt; no mutation",
        "produces": [
          "application/json"
        ],
        "responses": {
          "200": {
            "description": "Static simulated-write receipt",
            "schema": {
              "type": "object",
              "additionalProperties": false,
              "required": [
                "schema",
                "generated",
                "adapter_id",
                "capability_code",
                "route_count",
                "write_intent_count",
                "receipt"
              ],
              "properties": {
                "schema": {
                  "type": "string",
                  "enum": [
                    "rapp-static-industry-write-receipt/1.0"
                  ]
                },
                "generated": {
                  "type": "string",
                  "format": "date-time"
                },
                "adapter_id": {
                  "type": "string",
                  "enum": [
                    "service_now"
                  ]
                },
                "capability_code": {
                  "type": "string",
                  "enum": [
                    "analyzepriority"
                  ]
                },
                "route_count": {
                  "type": "integer",
                  "format": "int32"
                },
                "write_intent_count": {
                  "type": "integer",
                  "format": "int32"
                },
                "receipt": {
                  "type": "object",
                  "additionalProperties": false,
                  "required": [
                    "receipt_id",
                    "operation",
                    "resource_id",
                    "accepted",
                    "simulated",
                    "status",
                    "processed_at",
                    "idempotency_key"
                  ],
                  "properties": {
                    "receipt_id": {
                      "type": "string"
                    },
                    "operation": {
                      "type": "string"
                    },
                    "resource_id": {
                      "type": "string"
                    },
                    "accepted": {
                      "type": "boolean"
                    },
                    "simulated": {
                      "type": "boolean",
                      "enum": [
                        true
                      ]
                    },
                    "status": {
                      "type": "string",
                      "enum": [
                        "accepted",
                        "rejected",
                        "validation_failed"
                      ]
                    },
                    "processed_at": {
                      "type": "string",
                      "format": "date-time"
                    },
                    "idempotency_key": {
                      "type": "string"
                    }
                  }
                }
              }
            }
          }
        },
        "x-ms-visibility": "advanced"
      }
    },
    "/api/v1/service_now/receipts/calculatepriority.json": {
      "get": {
        "operationId": "SimulateServiceNowCalculatepriority",
        "summary": "Get a deterministic write-simulation receipt; no mutation",
        "produces": [
          "application/json"
        ],
        "responses": {
          "200": {
            "description": "Static simulated-write receipt",
            "schema": {
              "type": "object",
              "additionalProperties": false,
              "required": [
                "schema",
                "generated",
                "adapter_id",
                "capability_code",
                "route_count",
                "write_intent_count",
                "receipt"
              ],
              "properties": {
                "schema": {
                  "type": "string",
                  "enum": [
                    "rapp-static-industry-write-receipt/1.0"
                  ]
                },
                "generated": {
                  "type": "string",
                  "format": "date-time"
                },
                "adapter_id": {
                  "type": "string",
                  "enum": [
                    "service_now"
                  ]
                },
                "capability_code": {
                  "type": "string",
                  "enum": [
                    "calculatepriority"
                  ]
                },
                "route_count": {
                  "type": "integer",
                  "format": "int32"
                },
                "write_intent_count": {
                  "type": "integer",
                  "format": "int32"
                },
                "receipt": {
                  "type": "object",
                  "additionalProperties": false,
                  "required": [
                    "receipt_id",
                    "operation",
                    "resource_id",
                    "accepted",
                    "simulated",
                    "status",
                    "processed_at",
                    "idempotency_key"
                  ],
                  "properties": {
                    "receipt_id": {
                      "type": "string"
                    },
                    "operation": {
                      "type": "string"
                    },
                    "resource_id": {
                      "type": "string"
                    },
                    "accepted": {
                      "type": "boolean"
                    },
                    "simulated": {
                      "type": "boolean",
                      "enum": [
                        true
                      ]
                    },
                    "status": {
                      "type": "string",
                      "enum": [
                        "accepted",
                        "rejected",
                        "validation_failed"
                      ]
                    },
                    "processed_at": {
                      "type": "string",
                      "format": "date-time"
                    },
                    "idempotency_key": {
                      "type": "string"
                    }
                  }
                }
              }
            }
          }
        },
        "x-ms-visibility": "advanced"
      }
    },
    "/api/v1/service_now/receipts/determinerouting.json": {
      "get": {
        "operationId": "SimulateServiceNowDeterminerouting",
        "summary": "Get a deterministic write-simulation receipt; no mutation",
        "produces": [
          "application/json"
        ],
        "responses": {
          "200": {
            "description": "Static simulated-write receipt",
            "schema": {
              "type": "object",
              "additionalProperties": false,
              "required": [
                "schema",
                "generated",
                "adapter_id",
                "capability_code",
                "route_count",
                "write_intent_count",
                "receipt"
              ],
              "properties": {
                "schema": {
                  "type": "string",
                  "enum": [
                    "rapp-static-industry-write-receipt/1.0"
                  ]
                },
                "generated": {
                  "type": "string",
                  "format": "date-time"
                },
                "adapter_id": {
                  "type": "string",
                  "enum": [
                    "service_now"
                  ]
                },
                "capability_code": {
                  "type": "string",
                  "enum": [
                    "determinerouting"
                  ]
                },
                "route_count": {
                  "type": "integer",
                  "format": "int32"
                },
                "write_intent_count": {
                  "type": "integer",
                  "format": "int32"
                },
                "receipt": {
                  "type": "object",
                  "additionalProperties": false,
                  "required": [
                    "receipt_id",
                    "operation",
                    "resource_id",
                    "accepted",
                    "simulated",
                    "status",
                    "processed_at",
                    "idempotency_key"
                  ],
                  "properties": {
                    "receipt_id": {
                      "type": "string"
                    },
                    "operation": {
                      "type": "string"
                    },
                    "resource_id": {
                      "type": "string"
                    },
                    "accepted": {
                      "type": "boolean"
                    },
                    "simulated": {
                      "type": "boolean",
                      "enum": [
                        true
                      ]
                    },
                    "status": {
                      "type": "string",
                      "enum": [
                        "accepted",
                        "rejected",
                        "validation_failed"
                      ]
                    },
                    "processed_at": {
                      "type": "string",
                      "format": "date-time"
                    },
                    "idempotency_key": {
                      "type": "string"
                    }
                  }
                }
              }
            }
          }
        },
        "x-ms-visibility": "advanced"
      }
    },
    "/api/v1/service_now/receipts/execute.json": {
      "get": {
        "operationId": "SimulateServiceNowExecute",
        "summary": "Get a deterministic write-simulation receipt; no mutation",
        "produces": [
          "application/json"
        ],
        "responses": {
          "200": {
            "description": "Static simulated-write receipt",
            "schema": {
              "type": "object",
              "additionalProperties": false,
              "required": [
                "schema",
                "generated",
                "adapter_id",
                "capability_code",
                "route_count",
                "write_intent_count",
                "receipt"
              ],
              "properties": {
                "schema": {
                  "type": "string",
                  "enum": [
                    "rapp-static-industry-write-receipt/1.0"
                  ]
                },
                "generated": {
                  "type": "string",
                  "format": "date-time"
                },
                "adapter_id": {
                  "type": "string",
                  "enum": [
                    "service_now"
                  ]
                },
                "capability_code": {
                  "type": "string",
                  "enum": [
                    "execute"
                  ]
                },
                "route_count": {
                  "type": "integer",
                  "format": "int32"
                },
                "write_intent_count": {
                  "type": "integer",
                  "format": "int32"
                },
                "receipt": {
                  "type": "object",
                  "additionalProperties": false,
                  "required": [
                    "receipt_id",
                    "operation",
                    "resource_id",
                    "accepted",
                    "simulated",
                    "status",
                    "processed_at",
                    "idempotency_key"
                  ],
                  "properties": {
                    "receipt_id": {
                      "type": "string"
                    },
                    "operation": {
                      "type": "string"
                    },
                    "resource_id": {
                      "type": "string"
                    },
                    "accepted": {
                      "type": "boolean"
                    },
                    "simulated": {
                      "type": "boolean",
                      "enum": [
                        true
                      ]
                    },
                    "status": {
                      "type": "string",
                      "enum": [
                        "accepted",
                        "rejected",
                        "validation_failed"
                      ]
                    },
                    "processed_at": {
                      "type": "string",
                      "format": "date-time"
                    },
                    "idempotency_key": {
                      "type": "string"
                    }
                  }
                }
              }
            }
          }
        },
        "x-ms-visibility": "advanced"
      }
    },
    "/api/v1/service_now/receipts/optimize.json": {
      "get": {
        "operationId": "SimulateServiceNowOptimize",
        "summary": "Get a deterministic write-simulation receipt; no mutation",
        "produces": [
          "application/json"
        ],
        "responses": {
          "200": {
            "description": "Static simulated-write receipt",
            "schema": {
              "type": "object",
              "additionalProperties": false,
              "required": [
                "schema",
                "generated",
                "adapter_id",
                "capability_code",
                "route_count",
                "write_intent_count",
                "receipt"
              ],
              "properties": {
                "schema": {
                  "type": "string",
                  "enum": [
                    "rapp-static-industry-write-receipt/1.0"
                  ]
                },
                "generated": {
                  "type": "string",
                  "format": "date-time"
                },
                "adapter_id": {
                  "type": "string",
                  "enum": [
                    "service_now"
                  ]
                },
                "capability_code": {
                  "type": "string",
                  "enum": [
                    "optimize"
                  ]
                },
                "route_count": {
                  "type": "integer",
                  "format": "int32"
                },
                "write_intent_count": {
                  "type": "integer",
                  "format": "int32"
                },
                "receipt": {
                  "type": "object",
                  "additionalProperties": false,
                  "required": [
                    "receipt_id",
                    "operation",
                    "resource_id",
                    "accepted",
                    "simulated",
                    "status",
                    "processed_at",
                    "idempotency_key"
                  ],
                  "properties": {
                    "receipt_id": {
                      "type": "string"
                    },
                    "operation": {
                      "type": "string"
                    },
                    "resource_id": {
                      "type": "string"
                    },
                    "accepted": {
                      "type": "boolean"
                    },
                    "simulated": {
                      "type": "boolean",
                      "enum": [
                        true
                      ]
                    },
                    "status": {
                      "type": "string",
                      "enum": [
                        "accepted",
                        "rejected",
                        "validation_failed"
                      ]
                    },
                    "processed_at": {
                      "type": "string",
                      "format": "date-time"
                    },
                    "idempotency_key": {
                      "type": "string"
                    }
                  }
                }
              }
            }
          }
        },
        "x-ms-visibility": "advanced"
      }
    },
    "/api/v1/service_now/receipts/processticket.json": {
      "get": {
        "operationId": "SimulateServiceNowProcessticket",
        "summary": "Get a deterministic write-simulation receipt; no mutation",
        "produces": [
          "application/json"
        ],
        "responses": {
          "200": {
            "description": "Static simulated-write receipt",
            "schema": {
              "type": "object",
              "additionalProperties": false,
              "required": [
                "schema",
                "generated",
                "adapter_id",
                "capability_code",
                "route_count",
                "write_intent_count",
                "receipt"
              ],
              "properties": {
                "schema": {
                  "type": "string",
                  "enum": [
                    "rapp-static-industry-write-receipt/1.0"
                  ]
                },
                "generated": {
                  "type": "string",
                  "format": "date-time"
                },
                "adapter_id": {
                  "type": "string",
                  "enum": [
                    "service_now"
                  ]
                },
                "capability_code": {
                  "type": "string",
                  "enum": [
                    "processticket"
                  ]
                },
                "route_count": {
                  "type": "integer",
                  "format": "int32"
                },
                "write_intent_count": {
                  "type": "integer",
                  "format": "int32"
                },
                "receipt": {
                  "type": "object",
                  "additionalProperties": false,
                  "required": [
                    "receipt_id",
                    "operation",
                    "resource_id",
                    "accepted",
                    "simulated",
                    "status",
                    "processed_at",
                    "idempotency_key"
                  ],
                  "properties": {
                    "receipt_id": {
                      "type": "string"
                    },
                    "operation": {
                      "type": "string"
                    },
                    "resource_id": {
                      "type": "string"
                    },
                    "accepted": {
                      "type": "boolean"
                    },
                    "simulated": {
                      "type": "boolean",
                      "enum": [
                        true
                      ]
                    },
                    "status": {
                      "type": "string",
                      "enum": [
                        "accepted",
                        "rejected",
                        "validation_failed"
                      ]
                    },
                    "processed_at": {
                      "type": "string",
                      "format": "date-time"
                    },
                    "idempotency_key": {
                      "type": "string"
                    }
                  }
                }
              }
            }
          }
        },
        "x-ms-visibility": "advanced"
      }
    },
    "/api/v1/service_now/receipts/report.json": {
      "get": {
        "operationId": "SimulateServiceNowReport",
        "summary": "Get a deterministic write-simulation receipt; no mutation",
        "produces": [
          "application/json"
        ],
        "responses": {
          "200": {
            "description": "Static simulated-write receipt",
            "schema": {
              "type": "object",
              "additionalProperties": false,
              "required": [
                "schema",
                "generated",
                "adapter_id",
                "capability_code",
                "route_count",
                "write_intent_count",
                "receipt"
              ],
              "properties": {
                "schema": {
                  "type": "string",
                  "enum": [
                    "rapp-static-industry-write-receipt/1.0"
                  ]
                },
                "generated": {
                  "type": "string",
                  "format": "date-time"
                },
                "adapter_id": {
                  "type": "string",
                  "enum": [
                    "service_now"
                  ]
                },
                "capability_code": {
                  "type": "string",
                  "enum": [
                    "report"
                  ]
                },
                "route_count": {
                  "type": "integer",
                  "format": "int32"
                },
                "write_intent_count": {
                  "type": "integer",
                  "format": "int32"
                },
                "receipt": {
                  "type": "object",
                  "additionalProperties": false,
                  "required": [
                    "receipt_id",
                    "operation",
                    "resource_id",
                    "accepted",
                    "simulated",
                    "status",
                    "processed_at",
                    "idempotency_key"
                  ],
                  "properties": {
                    "receipt_id": {
                      "type": "string"
                    },
                    "operation": {
                      "type": "string"
                    },
                    "resource_id": {
                      "type": "string"
                    },
                    "accepted": {
                      "type": "boolean"
                    },
                    "simulated": {
                      "type": "boolean",
                      "enum": [
                        true
                      ]
                    },
                    "status": {
                      "type": "string",
                      "enum": [
                        "accepted",
                        "rejected",
                        "validation_failed"
                      ]
                    },
                    "processed_at": {
                      "type": "string",
                      "format": "date-time"
                    },
                    "idempotency_key": {
                      "type": "string"
                    }
                  }
                }
              }
            }
          }
        },
        "x-ms-visibility": "advanced"
      }
    },
    "/api/v1/service_now/tasks.json": {
      "get": {
        "operationId": "GetServiceNowTasksCollection",
        "summary": "List static tasks",
        "produces": [
          "application/json"
        ],
        "responses": {
          "200": {
            "description": "Deterministic no-PII collection",
            "schema": {
              "type": "object",
              "additionalProperties": false,
              "required": [
                "schema",
                "generated",
                "adapter_id",
                "resource_id",
                "count",
                "value"
              ],
              "properties": {
                "schema": {
                  "type": "string",
                  "enum": [
                    "rapp-static-industry-collection/1.0"
                  ]
                },
                "generated": {
                  "type": "string",
                  "format": "date-time"
                },
                "adapter_id": {
                  "type": "string",
                  "enum": [
                    "service_now"
                  ]
                },
                "resource_id": {
                  "type": "string",
                  "enum": [
                    "tasks"
                  ]
                },
                "count": {
                  "type": "integer",
                  "format": "int32"
                },
                "value": {
                  "type": "array",
                  "items": {
                    "type": "object",
                    "additionalProperties": false,
                    "required": [
                      "record_id",
                      "task_id",
                      "task_type",
                      "status",
                      "due_at"
                    ],
                    "properties": {
                      "record_id": {
                        "type": "string",
                        "description": "Stable deterministic record identifier."
                      },
                      "task_id": {
                        "type": "string"
                      },
                      "task_type": {
                        "type": "string"
                      },
                      "status": {
                        "type": "string"
                      },
                      "due_at": {
                        "type": "string",
                        "format": "date-time"
                      }
                    }
                  }
                }
              }
            }
          }
        },
        "x-ms-visibility": "important"
      }
    },
    "/api/v1/service_now/tasks/records/{record_id}.json": {
      "get": {
        "operationId": "GetServiceNowTasksRecord",
        "summary": "Get one static tasks record",
        "produces": [
          "application/json"
        ],
        "parameters": [
          {
            "name": "record_id",
            "in": "path",
            "required": true,
            "type": "string"
          }
        ],
        "responses": {
          "200": {
            "description": "Deterministic no-PII record",
            "schema": {
              "type": "object",
              "additionalProperties": false,
              "required": [
                "schema",
                "generated",
                "adapter_id",
                "resource_id",
                "record"
              ],
              "properties": {
                "schema": {
                  "type": "string",
                  "enum": [
                    "rapp-static-industry-record/1.0"
                  ]
                },
                "generated": {
                  "type": "string",
                  "format": "date-time"
                },
                "adapter_id": {
                  "type": "string",
                  "enum": [
                    "service_now"
                  ]
                },
                "resource_id": {
                  "type": "string",
                  "enum": [
                    "tasks"
                  ]
                },
                "record": {
                  "type": "object",
                  "additionalProperties": false,
                  "required": [
                    "record_id",
                    "task_id",
                    "task_type",
                    "status",
                    "due_at"
                  ],
                  "properties": {
                    "record_id": {
                      "type": "string",
                      "description": "Stable deterministic record identifier."
                    },
                    "task_id": {
                      "type": "string"
                    },
                    "task_type": {
                      "type": "string"
                    },
                    "status": {
                      "type": "string"
                    },
                    "due_at": {
                      "type": "string",
                      "format": "date-time"
                    }
                  }
                }
              }
            }
          },
          "404": {
            "description": "Unknown deterministic record ID"
          }
        },
        "x-ms-visibility": "important"
      }
    },
    "/api/v1/service_now/tickets.json": {
      "get": {
        "operationId": "GetServiceNowTicketsCollection",
        "summary": "List static tickets",
        "produces": [
          "application/json"
        ],
        "responses": {
          "200": {
            "description": "Deterministic no-PII collection",
            "schema": {
              "type": "object",
              "additionalProperties": false,
              "required": [
                "schema",
                "generated",
                "adapter_id",
                "resource_id",
                "count",
                "value"
              ],
              "properties": {
                "schema": {
                  "type": "string",
                  "enum": [
                    "rapp-static-industry-collection/1.0"
                  ]
                },
                "generated": {
                  "type": "string",
                  "format": "date-time"
                },
                "adapter_id": {
                  "type": "string",
                  "enum": [
                    "service_now"
                  ]
                },
                "resource_id": {
                  "type": "string",
                  "enum": [
                    "tickets"
                  ]
                },
                "count": {
                  "type": "integer",
                  "format": "int32"
                },
                "value": {
                  "type": "array",
                  "items": {
                    "type": "object",
                    "additionalProperties": false,
                    "required": [
                      "record_id",
                      "ticket_id",
                      "category_code",
                      "priority_code",
                      "status"
                    ],
                    "properties": {
                      "record_id": {
                        "type": "string",
                        "description": "Stable deterministic record identifier."
                      },
                      "ticket_id": {
                        "type": "string"
                      },
                      "category_code": {
                        "type": "string"
                      },
                      "priority_code": {
                        "type": "string"
                      },
                      "status": {
                        "type": "string"
                      }
                    }
                  }
                }
              }
            }
          }
        },
        "x-ms-visibility": "important"
      }
    },
    "/api/v1/service_now/tickets/records/{record_id}.json": {
      "get": {
        "operationId": "GetServiceNowTicketsRecord",
        "summary": "Get one static tickets record",
        "produces": [
          "application/json"
        ],
        "parameters": [
          {
            "name": "record_id",
            "in": "path",
            "required": true,
            "type": "string"
          }
        ],
        "responses": {
          "200": {
            "description": "Deterministic no-PII record",
            "schema": {
              "type": "object",
              "additionalProperties": false,
              "required": [
                "schema",
                "generated",
                "adapter_id",
                "resource_id",
                "record"
              ],
              "properties": {
                "schema": {
                  "type": "string",
                  "enum": [
                    "rapp-static-industry-record/1.0"
                  ]
                },
                "generated": {
                  "type": "string",
                  "format": "date-time"
                },
                "adapter_id": {
                  "type": "string",
                  "enum": [
                    "service_now"
                  ]
                },
                "resource_id": {
                  "type": "string",
                  "enum": [
                    "tickets"
                  ]
                },
                "record": {
                  "type": "object",
                  "additionalProperties": false,
                  "required": [
                    "record_id",
                    "ticket_id",
                    "category_code",
                    "priority_code",
                    "status"
                  ],
                  "properties": {
                    "record_id": {
                      "type": "string",
                      "description": "Stable deterministic record identifier."
                    },
                    "ticket_id": {
                      "type": "string"
                    },
                    "category_code": {
                      "type": "string"
                    },
                    "priority_code": {
                      "type": "string"
                    },
                    "status": {
                      "type": "string"
                    }
                  }
                }
              }
            }
          },
          "404": {
            "description": "Unknown deterministic record ID"
          }
        },
        "x-ms-visibility": "important"
      }
    },
    "/api/v1/service_now/work_orders.json": {
      "get": {
        "operationId": "GetServiceNowWorkOrdersCollection",
        "summary": "List static work_orders",
        "produces": [
          "application/json"
        ],
        "responses": {
          "200": {
            "description": "Deterministic no-PII collection",
            "schema": {
              "type": "object",
              "additionalProperties": false,
              "required": [
                "schema",
                "generated",
                "adapter_id",
                "resource_id",
                "count",
                "value"
              ],
              "properties": {
                "schema": {
                  "type": "string",
                  "enum": [
                    "rapp-static-industry-collection/1.0"
                  ]
                },
                "generated": {
                  "type": "string",
                  "format": "date-time"
                },
                "adapter_id": {
                  "type": "string",
                  "enum": [
                    "service_now"
                  ]
                },
                "resource_id": {
                  "type": "string",
                  "enum": [
                    "work_orders"
                  ]
                },
                "count": {
                  "type": "integer",
                  "format": "int32"
                },
                "value": {
                  "type": "array",
                  "items": {
                    "type": "object",
                    "additionalProperties": false,
                    "required": [
                      "record_id",
                      "work_order_id",
                      "asset_id",
                      "priority_code",
                      "status"
                    ],
                    "properties": {
                      "record_id": {
                        "type": "string",
                        "description": "Stable deterministic record identifier."
                      },
                      "work_order_id": {
                        "type": "string"
                      },
                      "asset_id": {
                        "type": "string"
                      },
                      "priority_code": {
                        "type": "string"
                      },
                      "status": {
                        "type": "string"
                      }
                    }
                  }
                }
              }
            }
          }
        },
        "x-ms-visibility": "important"
      }
    },
    "/api/v1/service_now/work_orders/records/{record_id}.json": {
      "get": {
        "operationId": "GetServiceNowWorkOrdersRecord",
        "summary": "Get one static work_orders record",
        "produces": [
          "application/json"
        ],
        "parameters": [
          {
            "name": "record_id",
            "in": "path",
            "required": true,
            "type": "string"
          }
        ],
        "responses": {
          "200": {
            "description": "Deterministic no-PII record",
            "schema": {
              "type": "object",
              "additionalProperties": false,
              "required": [
                "schema",
                "generated",
                "adapter_id",
                "resource_id",
                "record"
              ],
              "properties": {
                "schema": {
                  "type": "string",
                  "enum": [
                    "rapp-static-industry-record/1.0"
                  ]
                },
                "generated": {
                  "type": "string",
                  "format": "date-time"
                },
                "adapter_id": {
                  "type": "string",
                  "enum": [
                    "service_now"
                  ]
                },
                "resource_id": {
                  "type": "string",
                  "enum": [
                    "work_orders"
                  ]
                },
                "record": {
                  "type": "object",
                  "additionalProperties": false,
                  "required": [
                    "record_id",
                    "work_order_id",
                    "asset_id",
                    "priority_code",
                    "status"
                  ],
                  "properties": {
                    "record_id": {
                      "type": "string",
                      "description": "Stable deterministic record identifier."
                    },
                    "work_order_id": {
                      "type": "string"
                    },
                    "asset_id": {
                      "type": "string"
                    },
                    "priority_code": {
                      "type": "string"
                    },
                    "status": {
                      "type": "string"
                    }
                  }
                }
              }
            }
          },
          "404": {
            "description": "Unknown deterministic record ID"
          }
        },
        "x-ms-visibility": "important"
      }
    }
  },
  "securityDefinitions": {},
  "security": [],
  "x-rapp-schema": "rapp-static-industry-connector/1.0",
  "x-rapp-adapter-id": "service_now",
  "x-rapp-generated": "2026-07-10T20:30:00Z"
}
